google_spreadsheet/__init__.py
google_spreadsheet/api.py
google_spreadsheet_py-0.0.1.dist-info/DESCRIPTION.rst
google_spreadsheet_py-0.0.1.dist-info/METADATA
google_spreadsheet_py-0.0.1.dist-info/RECORD
google_spreadsheet_py-0.0.1.dist-info/WHEEL
google_spreadsheet_py-0.0.1.dist-info/metadata.json
google_spreadsheet_py-0.0.1.dist-info/top_level.txt
google_spreadsheet_py-0.0.1.dist-info/zip-safe
