Metadata-Version: 2.0
Name: google-spreadsheet-py
Version: 0.0.1
Summary: A simple Python wrapper for the Google Spreadsheets API
Home-page: https://github.com/ratson/google-spreadsheet-py
Author: Ratson
Author-email: contact@ratson.name
License: BSD
Keywords: google,docs,spreadsheets,api
Platform: UNKNOWN
Classifier: Development Status :: 5 - Production/Stable
Classifier: Environment :: Console
Classifier: Intended Audience :: Developers
Classifier: Natural Language :: English
Classifier: Operating System :: OS Independent
Classifier: Programming Language :: Python
Classifier: Topic :: Software Development :: Libraries :: Python Modules
Classifier: Topic :: Internet :: WWW/HTTP :: Dynamic Content :: CGI Tools/Libraries
Classifier: Topic :: Utilities
Classifier: License :: OSI Approved :: BSD License
Requires-Dist: gdata
